partlet/__init__.py
partlet-0.0.1.dist-info/LICENSE
partlet-0.0.1.dist-info/METADATA
partlet-0.0.1.dist-info/WHEEL
partlet-0.0.1.dist-info/top_level.txt
partlet-0.0.1.dist-info/RECORD
