Metadata-Version: 2.1
Name: partlet
Version: 0.0.1
Summary: Partlet Decomposition of Sequences
Home-page: https://github.com/partlet/partlet
Author: Alex Fedotov
Author-email: alex.fedotov@aol.com
License: UNKNOWN
Platform: UNKNOWN
Classifier: Programming Language :: Python :: 3
Classifier: License :: OSI Approved :: MIT License
Classifier: Operating System :: OS Independent
Requires-Python: >=3.7
